ghlestimator/__init__.py
ghlestimator/ghlestimator.py
ghlestimator-1.0.0.dist-info/LICENSE
ghlestimator-1.0.0.dist-info/METADATA
ghlestimator-1.0.0.dist-info/WHEEL
ghlestimator-1.0.0.dist-info/top_level.txt
ghlestimator-1.0.0.dist-info/RECORD
