Metadata-Version: 2.1
Name: ghlestimator
Version: 1.0.0
Summary: Linear generalized Huber estimator compatible with scikit-learn.
Home-page: https://github.com/damiandraxler/ghlestimator
Author: Damian Draxler
Author-email: damiandraxler01@gmail.com
License: UNKNOWN
Platform: UNKNOWN
Classifier: Programming Language :: Python :: 3.7
Classifier: License :: OSI Approved :: MIT License
Classifier: Operating System :: OS Independent
Requires-Python: >=3.7
Requires-Dist: numpy (==1.18.1)
Requires-Dist: scipy (==1.4.1)
Requires-Dist: twine (==1.13.0)
